latexcor/.vscode/settings.json
latexcor/__init__.py
latexcor/__version__.py
latexcor/cli.py
latexcor/config.py
latexcor/config.yaml
latexcor/encoding_converter.py
latexcor/file_manager.py
latexcor/latex_compiler.py
latexcor/mermaid_processor.py
latexcor/tests/__init__.py
latexcor/tests/test_encoding_converter.py
latexcor/tests/test_file_manager.py
latexcor/tests/test_latex_compiler.py
latexcor/tests/test_mermaid_processor.py
latexcor/tests/test_utils.py
latexcor/utils.py
latexcor-0.3.4.dist-info/LICENSE
latexcor-0.3.4.dist-info/METADATA
latexcor-0.3.4.dist-info/WHEEL
latexcor-0.3.4.dist-info/entry_points.txt
latexcor-0.3.4.dist-info/RECORD
