Metadata-Version: 2.1
Name: latexcor
Version: 0.3.4
Summary: 
License: MIT
Author: infocornouaille
Author-email: 90894019+infocornouaille@users.noreply.github.com
Requires-Python: >=3.11,<4.0
Classifier: License :: OSI Approved :: MIT License
Classifier: Programming Language :: Python :: 3
Classifier: Programming Language :: Python :: 3.11
Classifier: Programming Language :: Python :: 3.12
Requires-Dist: PyYAML (>=6.0.2,<7.0.0)
Requires-Dist: chardet (>=5.2.0,<6.0.0)
Requires-Dist: dockercor (>=0.1.2,<0.2.0)
Requires-Dist: pydantic (>=2.9.2,<3.0.0)
Requires-Dist: python-slugify (>=7.0.0,<8.0.0)
Requires-Dist: rich (>=13.9.3,<14.0.0)
Requires-Dist: tomli (>=2.0.2,<3.0.0)
Requires-Dist: typer (>=0.12.5,<0.13.0)
Requires-Dist: watchdog (>=5.0.3,<6.0.0)
